imkin/__init__.py
imkin/main.py
imkin/parsers.py
imkin/utils.py
imkin-0.2.5.dist-info/LICENSE
imkin-0.2.5.dist-info/METADATA
imkin-0.2.5.dist-info/WHEEL
imkin-0.2.5.dist-info/top_level.txt
imkin-0.2.5.dist-info/RECORD
