Metadata-Version: 2.1
Name: imkin
Version: 0.2.5
Summary: Lightweight a movie and TV series data parser from imdb.com and kinopoisk.ru
Home-page: https://bitbucket.org/shllw/imkin/
Author: shllw
Author-email: shllw@yahoo.com
Keywords: parser imdb kinopoisk
Classifier: Programming Language :: Python :: 3
Classifier: Programming Language :: Python :: 3.6
Classifier: Programming Language :: Python :: 3.7
Classifier: License :: OSI Approved :: MIT License
Classifier: Development Status :: 5 - Production/Stable
Classifier: Intended Audience :: Developers
Classifier: Operating System :: POSIX :: Linux
License-File: LICENSE
